featurize_jupyterlab/__init__.py
featurize_jupyterlab/__main__.py
featurize_jupyterlab/append_sys_path.py
featurize_jupyterlab/cli.py
featurize_jupyterlab/config.py
featurize_jupyterlab/constants.py
featurize_jupyterlab/core.py
featurize_jupyterlab/handlers.py
featurize_jupyterlab/logger.py
featurize_jupyterlab/models.py
featurize_jupyterlab/package_manager.py
featurize_jupyterlab/rpc_server.py
featurize_jupyterlab/rpc_service.py
featurize_jupyterlab/seed.py
featurize_jupyterlab/transform.py
featurize_jupyterlab/utils.py
featurize_jupyterlab/proto/__init__.py
featurize_jupyterlab/proto/minetorch_pb2.py
featurize_jupyterlab/proto/minetorch_pb2_grpc.py
featurize_jupyterlab/tests/__init__.py
featurize_jupyterlab/tests/mock_components.py
featurize_jupyterlab/tests/mock_user_data.py
featurize_jupyterlab/tests/test_core.py
featurize_jupyterlab/tests/test_experiment.py
featurize_jupyterlab/tests/test_handlers.py
featurize_jupyterlab/tests/test_transformation.py
featurize_jupyterlab-0.0.20.dist-info/METADATA
featurize_jupyterlab-0.0.20.dist-info/WHEEL
featurize_jupyterlab-0.0.20.dist-info/entry_points.txt
featurize_jupyterlab-0.0.20.dist-info/top_level.txt
featurize_jupyterlab-0.0.20.dist-info/RECORD
