Metadata-Version: 2.1
Name: featurize-jupyterlab
Version: 0.0.20
Summary: A server extension for JupyterLab's featurize extension
Home-page: UNKNOWN
Author: 
License: UNKNOWN
Platform: UNKNOWN
Requires-Dist: jupyterlab
Requires-Dist: grpcio
Requires-Dist: protobuf
Requires-Dist: pystream-protobuf
Requires-Dist: jupyter-nbextensions-configurator
Requires-Dist: pytest
Requires-Dist: pytest-tornado
Requires-Dist: click
Requires-Dist: sqlalchemy
Requires-Dist: psycopg2
Requires-Dist: pyhumps
